{"Name":"Example.Image.Writer","ConfigurationID":"12562286-4937-6c7e-c1b4-7df8947a10c2","searchItems":[],"queryItems":[],"listItems":[],"messageItems":[{"Index":1,"Level":0,"Parameters":{"LeftCondition":"[COALESCE,text,q,{LENGTH}]","RightCondition":"0","Operator":">","IsAdvanced":"False"},"ActionType":"Condition-If","ChildActions":[{"Index":2,"Level":0,"Parameters":{"Type":"&lt;Action&gt;","Name":"TextToWrite","Value":"[|text,q]","SkipProcessing":"false","AssignmentType":"0"},"ActionType":"Action-Assignment","ChildActions":[]}]},{"Index":3,"Level":0,"Parameters":{},"ActionType":"Condition-Else","ChildActions":[{"Index":4,"Level":0,"Parameters":{"Type":"&lt;Action&gt;","Name":"TextToWrite","Value":"Place text=???? in your querystring to generate a text image","SkipProcessing":"false","AssignmentType":"0"},"ActionType":"Action-Assignment","ChildActions":[]}]},{"Index":5,"Level":0,"Parameters":{"SourceType":"Variable","SourceVariableType":"&lt;Custom&gt;","Source":"[TextToWrite,Action]","SourceQuery":"","DestinationType":"Response","DestinationVariableType":"","DestinationResponseType":"image/jpeg","SQLFirstRow":"false","ColumnMappings":"","DestinationQuery":"","RunAsProcess":"false","ProcessName":"","Destination":"","TransformType":"Image","ImageTransformType":"Draw.Text","ImageFont":"arial","ImageSize":"20","ImageSizeType":"px","ImageColor":"#000000","ImageBGColor":"#ffffff","ImageWidth":"","ImageWidthType":"px","ImageHeight":"","ImageHeightType":"px","ImageQuality":"90","XMLReadPath":"","XMLWritePath":"","FileTask":""},"ActionType":"Action-File","ChildActions":[]}],"recordsPerPage":"0","enableAlphaFilter":"false","enablePageSelection":"false","enableRecordsPerPage":"false","enableCustomPaging":"false","enableExcelExport":false,"enableHide_OnNoQuery":false,"enableHide_OnNoResults":false,"enableAdvancedParsing":true,"enableCompoundIIFConditions":"true","enableQueryDebug":"false","enableQueryDebug_Edit":"false","enableQueryDebug_Admin":"false","enableQueryDebug_Super":"false","enableQueryDebug_Log":false,"enableQueryDebug_ErrorLog":false,"autoRefreshInterval":"","skipRedirectActions":"false","skipSubqueryDebugging":"false","enableAdmin_Edit":true,"enableAdmin_Admin":false,"enableAdmin_Super":false,"BotRecordCount":0,"BotPageVariableName":null,"enableBotShowAllRecords":false,"enableBotDetection":false,"BotNonAjaxText":null,"disableOpenScript":false,"enableSilverlight":false,"enableAJAX":"false","enableAJAXCustomPaging":"false","enableAJAXCustomStatus":"false","enableAJAXPageHistory":"false","customAJAXPageHistory":"","enableAJAXManual":"false","includeJavascriptUtilities":"false","includeJavascriptValidation":"false","javascriptOnComplete":"","enableMultipleColumnSorting":"false","ModuleCommunicationMessageType":"","showAll":"true","useExplicitSystemVariables":"false","enabledForcedQuerySplit":"false","query":"","filter":"","customConnection":"","listItem":"","listAItem":"","defaultItem":"","noqueryItem":"","SearchQuery":"","SearchTitle":"","SearchLink":"","SearchAuthor":"","SearchDate":"","SearchKey":"","SearchContent":"","SearchDescription":"","Header":null,"Footer":null,"Title":null,"Version":"20","enableAJAXPaging":"false","javascriptInclude":[]}